sbalance/__init__.py
sbalance/__main__.py
sbalance/config.py
sbalance/fields.py
sbalance/sbalance.py
sbalance/slurm.py
sbalance/utils.py
slurm_sbalance-0.2.4.dist-info/LICENSE
slurm_sbalance-0.2.4.dist-info/METADATA
slurm_sbalance-0.2.4.dist-info/WHEEL
slurm_sbalance-0.2.4.dist-info/entry_points.txt
slurm_sbalance-0.2.4.dist-info/top_level.txt
slurm_sbalance-0.2.4.dist-info/RECORD
