Metadata-Version: 2.1
Name: slurm-sbalance
Version: 0.2.4
Summary: Slurm utility for checking account balance
Home-page: https://github.com/puttsk/slurm-sbalance
Author: Putt Sakdhnagool
Author-email: putt.sakdhnagool@nectec.or.th
License: UNKNOWN
Project-URL: Bug Reports, https://github.com/puttsk/slurm-sbalance/issues
Project-URL: Source, https://github.com/puttsk/slurm-sbalance/
Keywords: slurm
Platform: UNKNOWN
Classifier: Development Status :: 3 - Alpha
Classifier: Intended Audience :: System Administrators
Classifier: Topic :: System :: Systems Administration
Classifier: License :: OSI Approved :: MIT License
Classifier: Programming Language :: Python :: 3
Classifier: Programming Language :: Python :: 3.6
Requires-Python: !=3.0.*, !=3.1.*, !=3.2.*, !=3.3.*, !=3.4.*, !=3.5.*, <4
License-File: LICENSE
